confy_addons/__init__.py
confy_addons/core/__init__.py
confy_addons/core/abstract.py
confy_addons/core/constants.py
confy_addons/core/exceptions.py
confy_addons/core/mixins.py
confy_addons/encryption/__init__.py
confy_addons/encryption/aes.py
confy_addons/encryption/rsa.py
confy_addons/prefixes.py
confy_addons-1.1.0.dist-info/METADATA
confy_addons-1.1.0.dist-info/WHEEL
confy_addons-1.1.0.dist-info/licenses/LICENSE
confy_addons-1.1.0.dist-info/RECORD
