Metadata-Version: 2.4
Name: confy-addons
Version: 1.1.0
Summary: Componentes adicionais de aplicativos clientes Confy
License: GNU GENERAL PUBLIC LICENSE
License-File: LICENSE
Author: Henrique Sebastião
Author-email: contato@henriquesebastiao.com
Requires-Python: >=3.9.2,<4.0
Classifier: Development Status :: 5 - Production/Stable
Classifier: Intended Audience :: Developers
Classifier: Intended Audience :: Telecommunications Industry
Classifier: License :: OSI Approved :: GNU General Public License v3 (GPLv3)
Classifier: Natural Language :: English
Classifier: Operating System :: Microsoft :: Windows
Classifier: Operating System :: MacOS
Classifier: Operating System :: Unix
Classifier: Programming Language :: Python :: 3.9
Classifier: Programming Language :: Python :: 3.10
Classifier: Programming Language :: Python :: 3.11
Classifier: Programming Language :: Python :: 3.12
Classifier: Programming Language :: Python :: 3.13
Classifier: Programming Language :: Python :: 3.14
Classifier: Topic :: Communications :: Chat
Classifier: Topic :: Security :: Cryptography
Classifier: Topic :: Software Development :: Libraries :: Python Modules
Classifier: Topic :: Utilities
Requires-Dist: cryptography (>=45.0.7,<46.0.0)
Project-URL: Bug Tracker, https://github.com/confy-security/confy-addons/issues
Project-URL: Changelog, https://github.com/confy-security/confy-addons/blob/main/CHANGELOG
Project-URL: Source, https://github.com/confy-security/confy-addons
